karrio/mappers/dhl_express/__init__.py
karrio/mappers/dhl_express/mapper.py
karrio/mappers/dhl_express/proxy.py
karrio/mappers/dhl_express/settings.py
karrio/plugins/dhl_express/__init__.py
karrio/providers/dhl_express/__init__.py
karrio/providers/dhl_express/address.py
karrio/providers/dhl_express/error.py
karrio/providers/dhl_express/rate.py
karrio/providers/dhl_express/shipment.py
karrio/providers/dhl_express/tracking.py
karrio/providers/dhl_express/units.py
karrio/providers/dhl_express/utils.py
karrio/providers/dhl_express/pickup/__init__.py
karrio/providers/dhl_express/pickup/cancel.py
karrio/providers/dhl_express/pickup/create.py
karrio/providers/dhl_express/pickup/update.py
karrio/schemas/dhl_express/__init__.py
karrio/schemas/dhl_express/book_pickup_global_req_3_0.py
karrio/schemas/dhl_express/book_pickup_global_res_3_0.py
karrio/schemas/dhl_express/cancel_pickup_global_req_3_0.py
karrio/schemas/dhl_express/cancel_pickup_global_res.py
karrio/schemas/dhl_express/datatypes.py
karrio/schemas/dhl_express/datatypes_global.py
karrio/schemas/dhl_express/datatypes_global_v10.py
karrio/schemas/dhl_express/datatypes_global_v62.py
karrio/schemas/dhl_express/datatypes_global_v62b.py
karrio/schemas/dhl_express/dct_req_global_3_0.py
karrio/schemas/dhl_express/dct_requestdatatypes.py
karrio/schemas/dhl_express/dct_requestdatatypes_global.py
karrio/schemas/dhl_express/dct_response_global_3_0.py
karrio/schemas/dhl_express/dct_responsedatatypes_global.py
karrio/schemas/dhl_express/err_res.py
karrio/schemas/dhl_express/modify_pickup_global_req_3_0.py
karrio/schemas/dhl_express/modify_pickup_global_res_3_0.py
karrio/schemas/dhl_express/pickup_err_res.py
karrio/schemas/dhl_express/pickup_res.py
karrio/schemas/dhl_express/pickupdatatypes_global.py
karrio/schemas/dhl_express/pickupdatatypes_global_3_0.py
karrio/schemas/dhl_express/routing_global_req_2_0.py
karrio/schemas/dhl_express/routing_global_res.py
karrio/schemas/dhl_express/ship_val_err_res.py
karrio_dhl_express-2026.1.4.dist-info/METADATA
karrio_dhl_express-2026.1.4.dist-info/WHEEL
karrio_dhl_express-2026.1.4.dist-info/entry_points.txt
karrio_dhl_express-2026.1.4.dist-info/top_level.txt
karrio_dhl_express-2026.1.4.dist-info/RECORD
